LICENSE
MANIFEST.in
README.md
requirements.in
requirements_dev.txt
requirements_test.txt
setup.py
cfdibills/VERSION
cfdibills/__init__.py
cfdibills/api.py
cfdibills/errors.py
cfdibills/io.py
cfdibills/verifiers.py
cfdibills.egg-info/PKG-INFO
cfdibills.egg-info/SOURCES.txt
cfdibills.egg-info/dependency_links.txt
cfdibills.egg-info/requires.txt
cfdibills.egg-info/top_level.txt
cfdibills/schemas/__init__.py
cfdibills/schemas/catalogs.py
cfdibills/schemas/cfdi33.py
cfdibills/schemas/cfdi40.py
cfdibills/schemas/complementos.py
cfdibills/schemas/fields.py
cfdibills/schemas/mixins.py
cfdibills/schemas/validators.py