Metadata-Version: 2.1
Name: cfdibills
Version: 0.3.0
Summary: Read and verify CFDI bills via SAT's web service
Home-page: https://github.com/peguerosdc/cfdibills
Author: Carlos Pegueros
Author-email: peguerosdc@gmail.com
License: LGPGLv3
Keywords: cfdi,facturacion,sat,mexico
Platform: UNKNOWN
Classifier: Programming Language :: Python :: 3.8
Classifier: Programming Language :: Python :: 3.9
Provides-Extra: dev
Provides-Extra: test
License-File: LICENSE
